{"devicePlatform":"","logFolder":"C:\\Users\\ALIMSAPUTRA\\Katalon Studio\\Astra Movic\\Reports\\Mobile\\Become Owner\\20180611_161905","runData":{"hostName":"ALIMSAPUTRA - DESKTOP-5G7MA8C","os":"Windows 10 64bit","katalonVersion":"5.3.0.1","deviceOS":"Android","appiumVersion":"1.8.1","deviceModel":"SM-J320G","hostAddress":"10.10.10.191","deviceManufacturer":"samsung","deviceId":"4200d20faae66400","deviceName":"samsung SM-J320G (Android 5.1.1)","deviceOSVersion":"5.1.1"},"type":"TEST_SUITE","name":"Become Owner","id":"Test Suites/Mobile/Become Owner","source":"","message":"Test Cases/Mobile/Android/Owner/SC99 Regression/TC01 Become Owner FAILED because (of) Unable to click on object \u0027Object Repository/Mobile/OR Become Owner/android.widget.Button0 - Next\u0027 (Root cause: com.kms.katalon.core.webui.exception.BrowserNotOpenedException: Browser is not opened\nBuild info: version: \u00273.7.1\u0027, revision: \u00278a0099a\u0027, time: \u00272017-11-06T21:07:36.161Z\u0027\nSystem info: host: \u0027DESKTOP-5G7MA8C\u0027, ip: \u002710.10.10.191\u0027, os.name: \u0027Windows 10\u0027, os.arch: \u0027amd64\u0027, os.version: \u002710.0\u0027, java.version: \u00271.8.0_102\u0027\nDriver info: driver.version: unknown)","description":"","startTime":1528708748867,"endTime":1528708954168,"childRecords":[{"isOptional":false,"type":"TEST_CASE","name":"Test Cases/Mobile/Android/User/SC99 Regression/TC04 Login biasa with email","id":"Test Cases/Mobile/Android/User/SC99 Regression/TC04 Login biasa with email","source":"C:\\\\Users\\\\ALIMSAPUTRA\\\\Katalon Studio\\\\Astra Movic\\\\Test Cases\\\\Mobile\\\\Android\\\\User\\\\SC99 Regression\\\\TC04 Login biasa with email.tc","message":"Test Cases/Mobile/Android/User/SC99 Regression/TC04 Login biasa with email","description":"","startTime":1528708749712,"endTime":1528708867545,"childRecords":[{"testStatus":{"stackTrace":"","statusValue":"INFO"},"type":"MESSAGE","name":"","message":"Evaluating variables for test case","startTime":1528708749813,"endTime":0,"childRecords":[],"interuppted":false},{"index":1,"isIgnoredIfFailed":false,"type":"TEST_STEP","name":"startApplication","message":"Started app at: \u0027C:\\Users\\ALIMSAPUTRA\\Downloads\\Movic_0.3.2_2018-05-30-debug.apk\u0027","description":"Buka browser","startTime":1528708750504,"endTime":1528708822537,"childRecords":[{"testStatus":{"stackTrace":"","statusValue":"PASSED"},"type":"MESSAGE","name":"","message":"Started app at: \u0027C:\\Users\\ALIMSAPUTRA\\Downloads\\Movic_0.3.2_2018-05-30-debug.apk\u0027","startTime":1528708822534,"endTime":0,"childRecords":[],"interuppted":false}],"interuppted":false},{"index":2,"isIgnoredIfFailed":false,"type":"TEST_STEP","name":"tap","message":"Tapped on element \u0027Object Repository/Mobile/OR Login biasa with email/android.widget.TextView3 - Indonesia\u0027","description":"Pilih bahasa indonesia","startTime":1528708822537,"endTime":1528708825833,"childRecords":[{"testStatus":{"stackTrace":"","statusValue":"WARNING"},"type":"MESSAGE","name":"","message":"Timeout \u00270\u0027 is invalid. Using default page load timeout: \u002730\u0027","startTime":1528708822613,"endTime":0,"childRecords":[],"interuppted":false},{"testStatus":{"stackTrace":"","statusValue":"PASSED"},"type":"MESSAGE","name":"","message":"Tapped on element \u0027Object Repository/Mobile/OR Login biasa with email/android.widget.TextView3 - Indonesia\u0027","startTime":1528708825832,"endTime":0,"childRecords":[],"interuppted":false}],"interuppted":false},{"index":3,"isIgnoredIfFailed":false,"type":"TEST_STEP","name":"tap","message":"Tapped on element \u0027Object Repository/Mobile/OR Login biasa with email/android.widget.ImageView4\u0027","description":"Tap arrow next","startTime":1528708825834,"endTime":1528708827356,"childRecords":[{"testStatus":{"stackTrace":"","statusValue":"WARNING"},"type":"MESSAGE","name":"","message":"Timeout \u00270\u0027 is invalid. Using default page load timeout: \u002730\u0027","startTime":1528708825851,"endTime":0,"childRecords":[],"interuppted":false},{"testStatus":{"stackTrace":"","statusValue":"PASSED"},"type":"MESSAGE","name":"","message":"Tapped on element \u0027Object Repository/Mobile/OR Login biasa with email/android.widget.ImageView4\u0027","startTime":1528708827354,"endTime":0,"childRecords":[],"interuppted":false}],"interuppted":false},{"index":4,"isIgnoredIfFailed":false,"type":"TEST_STEP","name":"tap","message":"Tapped on element \u0027Object Repository/Mobile/OR Login biasa with email/android.widget.TextView2 - Lewati\u0027","description":"Tap tombol \\\"Lewati\\\"","startTime":1528708827356,"endTime":1528708829308,"childRecords":[{"testStatus":{"stackTrace":"","statusValue":"WARNING"},"type":"MESSAGE","name":"","message":"Timeout \u00270\u0027 is invalid. Using default page load timeout: \u002730\u0027","startTime":1528708827370,"endTime":0,"childRecords":[],"interuppted":false},{"testStatus":{"stackTrace":"","statusValue":"PASSED"},"type":"MESSAGE","name":"","message":"Tapped on element \u0027Object Repository/Mobile/OR Login biasa with email/android.widget.TextView2 - Lewati\u0027","startTime":1528708829307,"endTime":0,"childRecords":[],"interuppted":false}],"interuppted":false},{"index":5,"isIgnoredIfFailed":false,"type":"TEST_STEP","name":"tap","message":"Tapped on element \u0027Object Repository/Mobile/OR Login biasa with email/android.widget.TextView0 - Log in\u0027","description":"Tap tombol \\\"Login\\\"","startTime":1528708829309,"endTime":1528708830773,"childRecords":[{"testStatus":{"stackTrace":"","statusValue":"WARNING"},"type":"MESSAGE","name":"","message":"Timeout \u00270\u0027 is invalid. Using default page load timeout: \u002730\u0027","startTime":1528708829323,"endTime":0,"childRecords":[],"interuppted":false},{"testStatus":{"stackTrace":"","statusValue":"PASSED"},"type":"MESSAGE","name":"","message":"Tapped on element \u0027Object Repository/Mobile/OR Login biasa with email/android.widget.TextView0 - Log in\u0027","startTime":1528708830772,"endTime":0,"childRecords":[],"interuppted":false}],"interuppted":false},{"index":6,"isIgnoredIfFailed":false,"type":"TEST_STEP","name":"setText","message":"Text \u0027ali.saputra@wgs.co.id\u0027 has been set to element \u0027Object Repository/Mobile/OR Login biasa with email/android.widget.EditText0\u0027","description":"Masukkan email","startTime":1528708830774,"endTime":1528708841997,"childRecords":[{"testStatus":{"stackTrace":"","statusValue":"WARNING"},"type":"MESSAGE","name":"","message":"Timeout \u00270\u0027 is invalid. Using default page load timeout: \u002730\u0027","startTime":1528708830807,"endTime":0,"childRecords":[],"interuppted":false},{"testStatus":{"stackTrace":"","statusValue":"PASSED"},"type":"MESSAGE","name":"","message":"Text \u0027ali.saputra@wgs.co.id\u0027 has been set to element \u0027Object Repository/Mobile/OR Login biasa with email/android.widget.EditText0\u0027","startTime":1528708841995,"endTime":0,"childRecords":[],"interuppted":false}],"interuppted":false},{"index":7,"isIgnoredIfFailed":false,"type":"TEST_STEP","name":"tap","message":"Tapped on element \u0027Object Repository/Mobile/OR Login biasa with email/android.widget.Button0 - Next\u0027","description":"Tap tombol \\\"Next\\\"","startTime":1528708841998,"endTime":1528708843156,"childRecords":[{"testStatus":{"stackTrace":"","statusValue":"WARNING"},"type":"MESSAGE","name":"","message":"Timeout \u00270\u0027 is invalid. Using default page load timeout: \u002730\u0027","startTime":1528708842008,"endTime":0,"childRecords":[],"interuppted":false},{"testStatus":{"stackTrace":"","statusValue":"PASSED"},"type":"MESSAGE","name":"","message":"Tapped on element \u0027Object Repository/Mobile/OR Login biasa with email/android.widget.Button0 - Next\u0027","startTime":1528708843154,"endTime":0,"childRecords":[],"interuppted":false}],"interuppted":false},{"index":8,"isIgnoredIfFailed":false,"type":"TEST_STEP","name":"tap","message":"Tapped on element \u0027Object Repository/Mobile/OR Login biasa with email/android.widget.EditText0 (1)\u0027","description":"Tap field password","startTime":1528708843156,"endTime":1528708848699,"childRecords":[{"testStatus":{"stackTrace":"","statusValue":"WARNING"},"type":"MESSAGE","name":"","message":"Timeout \u00270\u0027 is invalid. Using default page load timeout: \u002730\u0027","startTime":1528708843167,"endTime":0,"childRecords":[],"interuppted":false},{"testStatus":{"stackTrace":"","statusValue":"PASSED"},"type":"MESSAGE","name":"","message":"Tapped on element \u0027Object Repository/Mobile/OR Login biasa with email/android.widget.EditText0 (1)\u0027","startTime":1528708848697,"endTime":0,"childRecords":[],"interuppted":false}],"interuppted":false},{"index":9,"isIgnoredIfFailed":false,"type":"TEST_STEP","name":"setText","message":"Text \u0027Walden1234\u0027 has been set to element \u0027Object Repository/Mobile/OR Login biasa with email/android.widget.EditText0 (1)\u0027","description":"Masukkan password","startTime":1528708848699,"endTime":1528708862986,"childRecords":[{"testStatus":{"stackTrace":"","statusValue":"WARNING"},"type":"MESSAGE","name":"","message":"Timeout \u00270\u0027 is invalid. Using default page load timeout: \u002730\u0027","startTime":1528708848711,"endTime":0,"childRecords":[],"interuppted":false},{"testStatus":{"stackTrace":"","statusValue":"PASSED"},"type":"MESSAGE","name":"","message":"Text \u0027Walden1234\u0027 has been set to element \u0027Object Repository/Mobile/OR Login biasa with email/android.widget.EditText0 (1)\u0027","startTime":1528708862985,"endTime":0,"childRecords":[],"interuppted":false}],"interuppted":false},{"index":10,"isIgnoredIfFailed":false,"type":"TEST_STEP","name":"tap","message":"Tapped on element \u0027Object Repository/Mobile/OR Login biasa with email/android.widget.Button0 - Mulai Movic\u0027","description":"Tap tombol \\\"Mulai Movic\\\"","startTime":1528708862987,"endTime":1528708864106,"childRecords":[{"testStatus":{"stackTrace":"","statusValue":"WARNING"},"type":"MESSAGE","name":"","message":"Timeout \u00270\u0027 is invalid. Using default page load timeout: \u002730\u0027","startTime":1528708862996,"endTime":0,"childRecords":[],"interuppted":false},{"testStatus":{"stackTrace":"","statusValue":"PASSED"},"type":"MESSAGE","name":"","message":"Tapped on element \u0027Object Repository/Mobile/OR Login biasa with email/android.widget.Button0 - Mulai Movic\u0027","startTime":1528708864105,"endTime":0,"childRecords":[],"interuppted":false}],"interuppted":false},{"index":11,"isIgnoredIfFailed":false,"type":"TEST_STEP","name":"verifyElementVisible","message":"Element \u0027Object Repository/Mobile/OR Login biasa with email/android.widget.ImageView0\u0027 is visible","description":"Verifikasi image sesudah login","startTime":1528708864107,"endTime":1528708867533,"childRecords":[{"testStatus":{"stackTrace":"","statusValue":"WARNING"},"type":"MESSAGE","name":"","message":"Timeout \u00270\u0027 is invalid. Using default page load timeout: \u002730\u0027","startTime":1528708864144,"endTime":0,"childRecords":[],"interuppted":false},{"testStatus":{"stackTrace":"","statusValue":"PASSED"},"type":"MESSAGE","name":"","message":"Element \u0027Object Repository/Mobile/OR Login biasa with email/android.widget.ImageView0\u0027 is visible","startTime":1528708867532,"endTime":0,"childRecords":[],"interuppted":false}],"interuppted":false},{"index":12,"isIgnoredIfFailed":false,"type":"TEST_STEP","name":"closeApplication","message":"NOT_RUN: closeApplication","description":"","startTime":1528708867533,"endTime":1528708867535,"childRecords":[{"testStatus":{"stackTrace":"","statusValue":"NOT_RUN"},"type":"MESSAGE","name":"","message":"NOT_RUN: closeApplication","startTime":1528708867535,"endTime":0,"childRecords":[],"interuppted":false}],"interuppted":false},{"testStatus":{"stackTrace":"","statusValue":"PASSED"},"type":"MESSAGE","name":"","message":"Test Cases/Mobile/Android/User/SC99 Regression/TC04 Login biasa with email","startTime":1528708867536,"endTime":0,"childRecords":[],"interuppted":false}],"interuppted":false},{"isOptional":false,"type":"TEST_CASE","name":"Test Cases/Mobile/Android/Owner/SC99 Regression/TC01 Become Owner","id":"Test Cases/Mobile/Android/Owner/SC99 Regression/TC01 Become Owner","source":"C:\\\\Users\\\\ALIMSAPUTRA\\\\Katalon Studio\\\\Astra Movic\\\\Test Cases\\\\Mobile\\\\Android\\\\Owner\\\\SC99 Regression\\\\TC01 Become Owner.tc","message":"Test Cases/Mobile/Android/Owner/SC99 Regression/TC01 Become Owner FAILED because (of) Unable to click on object \u0027Object Repository/Mobile/OR Become Owner/android.widget.Button0 - Next\u0027 (Root cause: com.kms.katalon.core.webui.exception.BrowserNotOpenedException: Browser is not opened\nBuild info: version: \u00273.7.1\u0027, revision: \u00278a0099a\u0027, time: \u00272017-11-06T21:07:36.161Z\u0027\nSystem info: host: \u0027DESKTOP-5G7MA8C\u0027, ip: \u002710.10.10.191\u0027, os.name: \u0027Windows 10\u0027, os.arch: \u0027amd64\u0027, os.version: \u002710.0\u0027, java.version: \u00271.8.0_102\u0027\nDriver info: driver.version: unknown)","description":"","startTime":1528708867549,"endTime":1528708948399,"childRecords":[{"testStatus":{"stackTrace":"","statusValue":"INFO"},"type":"MESSAGE","name":"","message":"Evaluating variables for test case","startTime":1528708867584,"endTime":0,"childRecords":[],"interuppted":false},{"index":1,"isIgnoredIfFailed":false,"type":"TEST_STEP","name":"startApplication","message":"NOT_RUN: startApplication","description":"","startTime":1528708868031,"endTime":1528708868033,"childRecords":[{"testStatus":{"stackTrace":"","statusValue":"NOT_RUN"},"type":"MESSAGE","name":"","message":"NOT_RUN: startApplication","startTime":1528708868032,"endTime":0,"childRecords":[],"interuppted":false}],"interuppted":false},{"index":2,"isIgnoredIfFailed":false,"type":"TEST_STEP","name":"tap","message":"Tapped on element \u0027Object Repository/Mobile/OR Become Owner/android.widget.ImageView0\u0027","description":"Tap image user","startTime":1528708868034,"endTime":1528708868727,"childRecords":[{"testStatus":{"stackTrace":"","statusValue":"WARNING"},"type":"MESSAGE","name":"","message":"Timeout \u00270\u0027 is invalid. Using default page load timeout: \u002730\u0027","startTime":1528708868083,"endTime":0,"childRecords":[],"interuppted":false},{"testStatus":{"stackTrace":"","statusValue":"PASSED"},"type":"MESSAGE","name":"","message":"Tapped on element \u0027Object Repository/Mobile/OR Become Owner/android.widget.ImageView0\u0027","startTime":1528708868726,"endTime":0,"childRecords":[],"interuppted":false}],"interuppted":false},{"index":3,"isIgnoredIfFailed":false,"type":"TEST_STEP","name":"tap","message":"Tapped on element \u0027Object Repository/Mobile/OR Become Owner/android.widget.TextView15 - Switch to vehicle owner\u0027","description":"Pilih menu switch to vehicle owner","startTime":1528708868728,"endTime":1528708870267,"childRecords":[{"testStatus":{"stackTrace":"","statusValue":"WARNING"},"type":"MESSAGE","name":"","message":"Timeout \u00270\u0027 is invalid. Using default page load timeout: \u002730\u0027","startTime":1528708868773,"endTime":0,"childRecords":[],"interuppted":false},{"testStatus":{"stackTrace":"","statusValue":"PASSED"},"type":"MESSAGE","name":"","message":"Tapped on element \u0027Object Repository/Mobile/OR Become Owner/android.widget.TextView15 - Switch to vehicle owner\u0027","startTime":1528708870265,"endTime":0,"childRecords":[],"interuppted":false}],"interuppted":false},{"index":4,"isIgnoredIfFailed":false,"type":"TEST_STEP","name":"tap","message":"Tapped on element \u0027Object Repository/Mobile/OR Become Owner/android.widget.Button0 - Get Started\u0027","description":"Tap tombol \\\"Get Started\\\"","startTime":1528708870267,"endTime":1528708872388,"childRecords":[{"testStatus":{"stackTrace":"","statusValue":"WARNING"},"type":"MESSAGE","name":"","message":"Timeout \u00270\u0027 is invalid. Using default page load timeout: \u002730\u0027","startTime":1528708870283,"endTime":0,"childRecords":[],"interuppted":false},{"testStatus":{"stackTrace":"","statusValue":"PASSED"},"type":"MESSAGE","name":"","message":"Tapped on element \u0027Object Repository/Mobile/OR Become Owner/android.widget.Button0 - Get Started\u0027","startTime":1528708872387,"endTime":0,"childRecords":[],"interuppted":false}],"interuppted":false},{"index":5,"isIgnoredIfFailed":false,"type":"TEST_STEP","name":"tap","message":"Tapped on element \u0027Object Repository/Mobile/OR Become Owner/android.widget.Button0 - Ok\u0027","description":"Tap tombol \\\"Ok\\\"","startTime":1528708872388,"endTime":1528708873655,"childRecords":[{"testStatus":{"stackTrace":"","statusValue":"WARNING"},"type":"MESSAGE","name":"","message":"Timeout \u00270\u0027 is invalid. Using default page load timeout: \u002730\u0027","startTime":1528708872433,"endTime":0,"childRecords":[],"interuppted":false},{"testStatus":{"stackTrace":"","statusValue":"PASSED"},"type":"MESSAGE","name":"","message":"Tapped on element \u0027Object Repository/Mobile/OR Become Owner/android.widget.Button0 - Ok\u0027","startTime":1528708873653,"endTime":0,"childRecords":[],"interuppted":false}],"interuppted":false},{"index":6,"isIgnoredIfFailed":false,"type":"TEST_STEP","name":"tap","message":"Tapped on element \u0027Object Repository/Mobile/OR Become Owner/android.widget.ImageView2\u0027","description":"Ambil photo dengan kamera","startTime":1528708873656,"endTime":1528708875504,"childRecords":[{"testStatus":{"stackTrace":"","statusValue":"WARNING"},"type":"MESSAGE","name":"","message":"Timeout \u00270\u0027 is invalid. Using default page load timeout: \u002730\u0027","startTime":1528708873725,"endTime":0,"childRecords":[],"interuppted":false},{"testStatus":{"stackTrace":"","statusValue":"PASSED"},"type":"MESSAGE","name":"","message":"Tapped on element \u0027Object Repository/Mobile/OR Become Owner/android.widget.ImageView2\u0027","startTime":1528708875503,"endTime":0,"childRecords":[],"interuppted":false}],"interuppted":false},{"index":7,"isIgnoredIfFailed":false,"type":"TEST_STEP","name":"tap","message":"Tapped on element \u0027Object Repository/Mobile/OR Become Owner/android.widget.Button0 - Use This Photo\u0027","description":"Tap tombol \\\"use this photo\\\"","startTime":1528708875505,"endTime":1528708876410,"childRecords":[{"testStatus":{"stackTrace":"","statusValue":"WARNING"},"type":"MESSAGE","name":"","message":"Timeout \u00270\u0027 is invalid. Using default page load timeout: \u002730\u0027","startTime":1528708875563,"endTime":0,"childRecords":[],"interuppted":false},{"testStatus":{"stackTrace":"","statusValue":"PASSED"},"type":"MESSAGE","name":"","message":"Tapped on element \u0027Object Repository/Mobile/OR Become Owner/android.widget.Button0 - Use This Photo\u0027","startTime":1528708876409,"endTime":0,"childRecords":[],"interuppted":false}],"interuppted":false},{"index":8,"isIgnoredIfFailed":false,"type":"TEST_STEP","name":"tap","message":"Tapped on element \u0027Object Repository/Mobile/OR Become Owner/android.widget.Button0 - Ok (1)\u0027","description":"Tap tombol \\\"Ok\\\"","startTime":1528708876411,"endTime":1528708882030,"childRecords":[{"testStatus":{"stackTrace":"","statusValue":"WARNING"},"type":"MESSAGE","name":"","message":"Timeout \u00270\u0027 is invalid. Using default page load timeout: \u002730\u0027","startTime":1528708876466,"endTime":0,"childRecords":[],"interuppted":false},{"testStatus":{"stackTrace":"","statusValue":"PASSED"},"type":"MESSAGE","name":"","message":"Tapped on element \u0027Object Repository/Mobile/OR Become Owner/android.widget.Button0 - Ok (1)\u0027","startTime":1528708882029,"endTime":0,"childRecords":[],"interuppted":false}],"interuppted":false},{"index":9,"isIgnoredIfFailed":false,"type":"TEST_STEP","name":"tap","message":"Tapped on element \u0027Object Repository/Mobile/OR Become Owner/android.widget.ImageView2\u0027","description":"Ambil photo dengan kamera","startTime":1528708882031,"endTime":1528708883486,"childRecords":[{"testStatus":{"stackTrace":"","statusValue":"WARNING"},"type":"MESSAGE","name":"","message":"Timeout \u00270\u0027 is invalid. Using default page load timeout: \u002730\u0027","startTime":1528708882041,"endTime":0,"childRecords":[],"interuppted":false},{"testStatus":{"stackTrace":"","statusValue":"PASSED"},"type":"MESSAGE","name":"","message":"Tapped on element \u0027Object Repository/Mobile/OR Become Owner/android.widget.ImageView2\u0027","startTime":1528708883484,"endTime":0,"childRecords":[],"interuppted":false}],"interuppted":false},{"index":10,"isIgnoredIfFailed":false,"type":"TEST_STEP","name":"tap","message":"Tapped on element \u0027Object Repository/Mobile/OR Become Owner/android.widget.Button0 - Use This Photo\u0027","description":"Tap tombol \\\"use this photo\\\"","startTime":1528708883486,"endTime":1528708884430,"childRecords":[{"testStatus":{"stackTrace":"","statusValue":"WARNING"},"type":"MESSAGE","name":"","message":"Timeout \u00270\u0027 is invalid. Using default page load timeout: \u002730\u0027","startTime":1528708883498,"endTime":0,"childRecords":[],"interuppted":false},{"testStatus":{"stackTrace":"","statusValue":"PASSED"},"type":"MESSAGE","name":"","message":"Tapped on element \u0027Object Repository/Mobile/OR Become Owner/android.widget.Button0 - Use This Photo\u0027","startTime":1528708884428,"endTime":0,"childRecords":[],"interuppted":false}],"interuppted":false},{"index":11,"isIgnoredIfFailed":false,"type":"TEST_STEP","name":"tap","message":"Tapped on element \u0027Object Repository/Mobile/OR Become Owner/android.widget.Button0 - Ok (1)\u0027","description":"Tap tombol \\\"Ok\\\"","startTime":1528708884430,"endTime":1528708889273,"childRecords":[{"testStatus":{"stackTrace":"","statusValue":"WARNING"},"type":"MESSAGE","name":"","message":"Timeout \u00270\u0027 is invalid. Using default page load timeout: \u002730\u0027","startTime":1528708884440,"endTime":0,"childRecords":[],"interuppted":false},{"testStatus":{"stackTrace":"","statusValue":"PASSED"},"type":"MESSAGE","name":"","message":"Tapped on element \u0027Object Repository/Mobile/OR Become Owner/android.widget.Button0 - Ok (1)\u0027","startTime":1528708889271,"endTime":0,"childRecords":[],"interuppted":false}],"interuppted":false},{"index":12,"isIgnoredIfFailed":false,"type":"TEST_STEP","name":"tap","message":"Tapped on element \u0027Object Repository/Mobile/OR Become Owner/android.widget.ImageView2\u0027","description":"Ambil photo dengan kamera","startTime":1528708889275,"endTime":1528708890844,"childRecords":[{"testStatus":{"stackTrace":"","statusValue":"WARNING"},"type":"MESSAGE","name":"","message":"Timeout \u00270\u0027 is invalid. Using default page load timeout: \u002730\u0027","startTime":1528708889287,"endTime":0,"childRecords":[],"interuppted":false},{"testStatus":{"stackTrace":"","statusValue":"PASSED"},"type":"MESSAGE","name":"","message":"Tapped on element \u0027Object Repository/Mobile/OR Become Owner/android.widget.ImageView2\u0027","startTime":1528708890843,"endTime":0,"childRecords":[],"interuppted":false}],"interuppted":false},{"index":13,"isIgnoredIfFailed":false,"type":"TEST_STEP","name":"tap","message":"Tapped on element \u0027Object Repository/Mobile/OR Become Owner/android.widget.Button0 - Use This Photo\u0027","description":"Tap tombol \\\"use this photo\\\"","startTime":1528708890844,"endTime":1528708891769,"childRecords":[{"testStatus":{"stackTrace":"","statusValue":"WARNING"},"type":"MESSAGE","name":"","message":"Timeout \u00270\u0027 is invalid. Using default page load timeout: \u002730\u0027","startTime":1528708890853,"endTime":0,"childRecords":[],"interuppted":false},{"testStatus":{"stackTrace":"","statusValue":"PASSED"},"type":"MESSAGE","name":"","message":"Tapped on element \u0027Object Repository/Mobile/OR Become Owner/android.widget.Button0 - Use This Photo\u0027","startTime":1528708891767,"endTime":0,"childRecords":[],"interuppted":false}],"interuppted":false},{"index":14,"isIgnoredIfFailed":false,"type":"TEST_STEP","name":"tap","message":"Tapped on element \u0027Object Repository/Mobile/OR Become Owner/android.widget.ImageView1\u0027","description":"Tap \\\"Add Photo\\\"","startTime":1528708891769,"endTime":1528708898135,"childRecords":[{"testStatus":{"stackTrace":"","statusValue":"WARNING"},"type":"MESSAGE","name":"","message":"Timeout \u00270\u0027 is invalid. Using default page load timeout: \u002730\u0027","startTime":1528708891816,"endTime":0,"childRecords":[],"interuppted":false},{"testStatus":{"stackTrace":"","statusValue":"PASSED"},"type":"MESSAGE","name":"","message":"Tapped on element \u0027Object Repository/Mobile/OR Become Owner/android.widget.ImageView1\u0027","startTime":1528708898134,"endTime":0,"childRecords":[],"interuppted":false}],"interuppted":false},{"index":15,"isIgnoredIfFailed":false,"type":"TEST_STEP","name":"tap","message":"Tapped on element \u0027Object Repository/Mobile/OR Become Owner/android.widget.ImageView2\u0027","description":"Ambil photo dengan kamera","startTime":1528708898136,"endTime":1528708899482,"childRecords":[{"testStatus":{"stackTrace":"","statusValue":"WARNING"},"type":"MESSAGE","name":"","message":"Timeout \u00270\u0027 is invalid. Using default page load timeout: \u002730\u0027","startTime":1528708898146,"endTime":0,"childRecords":[],"interuppted":false},{"testStatus":{"stackTrace":"","statusValue":"PASSED"},"type":"MESSAGE","name":"","message":"Tapped on element \u0027Object Repository/Mobile/OR Become Owner/android.widget.ImageView2\u0027","startTime":1528708899481,"endTime":0,"childRecords":[],"interuppted":false}],"interuppted":false},{"index":16,"isIgnoredIfFailed":false,"type":"TEST_STEP","name":"tap","message":"Tapped on element \u0027Object Repository/Mobile/OR Become Owner/android.widget.Button0 - Next\u0027","description":"Tap tombol \\\"Next\\\"","startTime":1528708899482,"endTime":1528708900918,"childRecords":[{"testStatus":{"stackTrace":"","statusValue":"WARNING"},"type":"MESSAGE","name":"","message":"Timeout \u00270\u0027 is invalid. Using default page load timeout: \u002730\u0027","startTime":1528708899522,"endTime":0,"childRecords":[],"interuppted":false},{"testStatus":{"stackTrace":"","statusValue":"PASSED"},"type":"MESSAGE","name":"","message":"Tapped on element \u0027Object Repository/Mobile/OR Become Owner/android.widget.Button0 - Next\u0027","startTime":1528708900917,"endTime":0,"childRecords":[],"interuppted":false}],"interuppted":false},{"index":17,"isIgnoredIfFailed":false,"type":"TEST_STEP","name":"setText","message":"Text \u0027Ali Rental\u0027 has been set to element \u0027Object Repository/Mobile/OR Become Owner/android.widget.EditText0\u0027","description":"Masukkan rental name","startTime":1528708900919,"endTime":1528708912969,"childRecords":[{"testStatus":{"stackTrace":"","statusValue":"WARNING"},"type":"MESSAGE","name":"","message":"Timeout \u00270\u0027 is invalid. Using default page load timeout: \u002730\u0027","startTime":1528708900954,"endTime":0,"childRecords":[],"interuppted":false},{"testStatus":{"stackTrace":"","statusValue":"PASSED"},"type":"MESSAGE","name":"","message":"Text \u0027Ali Rental\u0027 has been set to element \u0027Object Repository/Mobile/OR Become Owner/android.widget.EditText0\u0027","startTime":1528708912968,"endTime":0,"childRecords":[],"interuppted":false}],"interuppted":false},{"index":18,"isIgnoredIfFailed":false,"type":"TEST_STEP","name":"tap","message":"Tapped on element \u0027Object Repository/Mobile/OR Become Owner/android.widget.Button0 - Next (1)\u0027","description":"Tap tombol \\\"Next\\\"","startTime":1528708912969,"endTime":1528708913982,"childRecords":[{"testStatus":{"stackTrace":"","statusValue":"WARNING"},"type":"MESSAGE","name":"","message":"Timeout \u00270\u0027 is invalid. Using default page load timeout: \u002730\u0027","startTime":1528708913014,"endTime":0,"childRecords":[],"interuppted":false},{"testStatus":{"stackTrace":"","statusValue":"PASSED"},"type":"MESSAGE","name":"","message":"Tapped on element \u0027Object Repository/Mobile/OR Become Owner/android.widget.Button0 - Next (1)\u0027","startTime":1528708913982,"endTime":0,"childRecords":[],"interuppted":false}],"interuppted":false},{"index":19,"isIgnoredIfFailed":false,"type":"TEST_STEP","name":"tap","message":"Tapped on element \u0027Object Repository/Mobile/OR Become Owner/android.widget.LinearLayout3\u0027","description":"Tap \\\"Set Location\\\"","startTime":1528708913983,"endTime":1528708917002,"childRecords":[{"testStatus":{"stackTrace":"","statusValue":"WARNING"},"type":"MESSAGE","name":"","message":"Timeout \u00270\u0027 is invalid. Using default page load timeout: \u002730\u0027","startTime":1528708914021,"endTime":0,"childRecords":[],"interuppted":false},{"testStatus":{"stackTrace":"","statusValue":"PASSED"},"type":"MESSAGE","name":"","message":"Tapped on element \u0027Object Repository/Mobile/OR Become Owner/android.widget.LinearLayout3\u0027","startTime":1528708917001,"endTime":0,"childRecords":[],"interuppted":false}],"interuppted":false},{"index":20,"isIgnoredIfFailed":false,"type":"TEST_STEP","name":"tap","message":"Tapped on element \u0027Object Repository/Mobile/OR Become Owner/android.widget.Button0 - Confirm\u0027","description":"Tap tombol \\\"Confirm\\\"","startTime":1528708917003,"endTime":1528708920984,"childRecords":[{"testStatus":{"stackTrace":"","statusValue":"WARNING"},"type":"MESSAGE","name":"","message":"Timeout \u00270\u0027 is invalid. Using default page load timeout: \u002730\u0027","startTime":1528708917044,"endTime":0,"childRecords":[],"interuppted":false},{"testStatus":{"stackTrace":"","statusValue":"PASSED"},"type":"MESSAGE","name":"","message":"Tapped on element \u0027Object Repository/Mobile/OR Become Owner/android.widget.Button0 - Confirm\u0027","startTime":1528708920983,"endTime":0,"childRecords":[],"interuppted":false}],"interuppted":false},{"index":21,"isIgnoredIfFailed":false,"type":"TEST_STEP","name":"setText","message":"Text \u0027Bandung\u0027 has been set to element \u0027Object Repository/Mobile/OR Become Owner/android.widget.EditText0 (1)\u0027","description":"Masukkan city \\\"Bandung\\\"","startTime":1528708920985,"endTime":1528708932067,"childRecords":[{"testStatus":{"stackTrace":"","statusValue":"WARNING"},"type":"MESSAGE","name":"","message":"Timeout \u00270\u0027 is invalid. Using default page load timeout: \u002730\u0027","startTime":1528708920997,"endTime":0,"childRecords":[],"interuppted":false},{"testStatus":{"stackTrace":"","statusValue":"PASSED"},"type":"MESSAGE","name":"","message":"Text \u0027Bandung\u0027 has been set to element \u0027Object Repository/Mobile/OR Become Owner/android.widget.EditText0 (1)\u0027","startTime":1528708932066,"endTime":0,"childRecords":[],"interuppted":false}],"interuppted":false},{"index":22,"isIgnoredIfFailed":false,"type":"TEST_STEP","name":"tap","message":"Tapped on element \u0027Object Repository/Mobile/OR Become Owner/android.widget.LinearLayout6 - Complete Address (Optional)\u0027","description":"","startTime":1528708932068,"endTime":1528708933117,"childRecords":[{"testStatus":{"stackTrace":"","statusValue":"WARNING"},"type":"MESSAGE","name":"","message":"Timeout \u00270\u0027 is invalid. Using default page load timeout: \u002730\u0027","startTime":1528708932077,"endTime":0,"childRecords":[],"interuppted":false},{"testStatus":{"stackTrace":"","statusValue":"PASSED"},"type":"MESSAGE","name":"","message":"Tapped on element \u0027Object Repository/Mobile/OR Become Owner/android.widget.LinearLayout6 - Complete Address (Optional)\u0027","startTime":1528708933116,"endTime":0,"childRecords":[],"interuppted":false}],"interuppted":false},{"index":23,"isIgnoredIfFailed":false,"type":"TEST_STEP","name":"hideKeyboard","message":"Keyboard is hidden","description":"Hide keyboard","startTime":1528708933118,"endTime":1528708934180,"childRecords":[{"testStatus":{"stackTrace":"","statusValue":"PASSED"},"type":"MESSAGE","name":"","message":"Keyboard is hidden","startTime":1528708934108,"endTime":0,"childRecords":[],"interuppted":false}],"interuppted":false},{"index":24,"isIgnoredIfFailed":false,"type":"TEST_STEP","name":"tap","message":"Tapped on element \u0027Object Repository/Mobile/OR Become Owner/android.widget.Button0 - Next (2)\u0027","description":"Tap tombol \\\"Next\\\"","startTime":1528708934180,"endTime":1528708935484,"childRecords":[{"testStatus":{"stackTrace":"","statusValue":"WARNING"},"type":"MESSAGE","name":"","message":"Timeout \u00270\u0027 is invalid. Using default page load timeout: \u002730\u0027","startTime":1528708934197,"endTime":0,"childRecords":[],"interuppted":false},{"testStatus":{"stackTrace":"","statusValue":"PASSED"},"type":"MESSAGE","name":"","message":"Tapped on element \u0027Object Repository/Mobile/OR Become Owner/android.widget.Button0 - Next (2)\u0027","startTime":1528708935483,"endTime":0,"childRecords":[],"interuppted":false}],"interuppted":false},{"index":25,"isIgnoredIfFailed":false,"type":"TEST_STEP","name":"setText","message":"Text \u0027Cheap \u0026 Quality\u0027 has been set to element \u0027Object Repository/Mobile/OR Become Owner/android.widget.EditText0 (2)\u0027","description":"Masukkan slogan rental","startTime":1528708935484,"endTime":1528708946961,"childRecords":[{"testStatus":{"stackTrace":"","statusValue":"WARNING"},"type":"MESSAGE","name":"","message":"Timeout \u00270\u0027 is invalid. Using default page load timeout: \u002730\u0027","startTime":1528708935551,"endTime":0,"childRecords":[],"interuppted":false},{"testStatus":{"stackTrace":"","statusValue":"PASSED"},"type":"MESSAGE","name":"","message":"Text \u0027Cheap \u0026 Quality\u0027 has been set to element \u0027Object Repository/Mobile/OR Become Owner/android.widget.EditText0 (2)\u0027","startTime":1528708946959,"endTime":0,"childRecords":[],"interuppted":false}],"interuppted":false},{"index":26,"isIgnoredIfFailed":false,"type":"TEST_STEP","name":"hideKeyboard","message":"Keyboard is hidden","description":"Hide keyboard","startTime":1528708946961,"endTime":1528708947806,"childRecords":[{"testStatus":{"stackTrace":"","statusValue":"PASSED"},"type":"MESSAGE","name":"","message":"Keyboard is hidden","startTime":1528708947732,"endTime":0,"childRecords":[],"interuppted":false}],"interuppted":false},{"index":27,"isIgnoredIfFailed":false,"type":"TEST_STEP","name":"click","message":"Unable to click on object \u0027Object Repository/Mobile/OR Become Owner/android.widget.Button0 - Next\u0027 (Root cause: com.kms.katalon.core.webui.exception.BrowserNotOpenedException: Browser is not opened\nBuild info: version: \u00273.7.1\u0027, revision: \u00278a0099a\u0027, time: \u00272017-11-06T21:07:36.161Z\u0027\nSystem info: host: \u0027DESKTOP-5G7MA8C\u0027, ip: \u002710.10.10.191\u0027, os.name: \u0027Windows 10\u0027, os.arch: \u0027amd64\u0027, os.version: \u002710.0\u0027, java.version: \u00271.8.0_102\u0027\nDriver info: driver.version: unknown)","description":"Tap tombol \\\"Next\\\"","startTime":1528708947806,"endTime":1528708948395,"childRecords":[{"testStatus":{"stackTrace":"","statusValue":"WARNING"},"type":"MESSAGE","name":"","message":"Cannot take screenshot","startTime":1528708948384,"endTime":0,"childRecords":[],"interuppted":false},{"testStatus":{"stackTrace":"","statusValue":"FAILED"},"type":"MESSAGE","name":"","message":"Unable to click on object \u0027Object Repository/Mobile/OR Become Owner/android.widget.Button0 - Next\u0027 (Root cause: com.kms.katalon.core.webui.exception.BrowserNotOpenedException: Browser is not opened\nBuild info: version: \u00273.7.1\u0027, revision: \u00278a0099a\u0027, time: \u00272017-11-06T21:07:36.161Z\u0027\nSystem info: host: \u0027DESKTOP-5G7MA8C\u0027, ip: \u002710.10.10.191\u0027, os.name: \u0027Windows 10\u0027, os.arch: \u0027amd64\u0027, os.version: \u002710.0\u0027, java.version: \u00271.8.0_102\u0027\nDriver info: driver.version: unknown)","startTime":1528708948394,"endTime":0,"childRecords":[],"interuppted":false}],"interuppted":false},{"testStatus":{"stackTrace":"","statusValue":"FAILED"},"type":"MESSAGE","name":"","message":"Test Cases/Mobile/Android/Owner/SC99 Regression/TC01 Become Owner FAILED because (of) Unable to click on object \u0027Object Repository/Mobile/OR Become Owner/android.widget.Button0 - Next\u0027 (Root cause: com.kms.katalon.core.webui.exception.BrowserNotOpenedException: Browser is not opened\nBuild info: version: \u00273.7.1\u0027, revision: \u00278a0099a\u0027, time: \u00272017-11-06T21:07:36.161Z\u0027\nSystem info: host: \u0027DESKTOP-5G7MA8C\u0027, ip: \u002710.10.10.191\u0027, os.name: \u0027Windows 10\u0027, os.arch: \u0027amd64\u0027, os.version: \u002710.0\u0027, java.version: \u00271.8.0_102\u0027\nDriver info: driver.version: unknown)","startTime":1528708948396,"endTime":0,"childRecords":[],"interuppted":false}],"interuppted":false}],"interuppted":false}